<regions country="Qatar">
	<region name="Ad Dawhah" type="municipality" typeTranslated="baladiyah">
		<name normalized="Ad Dawhah" languages="English;official">Ad Dawhah</name>
		<name normalized="Ad-Dauha" languages="Polish">Ad-Dauha</name>
		<name normalized="Dauha" languages="Slovak">Dauha</name>
		<name normalized="Dauha" languages="Czech">Dauhá</name>
		<name normalized="Dawha" languages="Kabyle">Dawḥa</name>
		<name normalized="Doha" languages="Achinese;Afrikaans;Albanian;Azerbaijani;Basque;Bosnian;Breton;Catalan;Chinese (Min Nan);Croatian;Danish;Dutch;English;Estonian;Extremaduran;Fiji Hindi;Finnish;Franco-Provencal;French;Galician;German;Haitian;Hungarian;Icelandic;Ido;Iloko;Indonesian;Interlingue;Irish;Italian;Javanese;Kalaallisut;Kinyarwanda;Kurdish;Latin;Latvian;Lithuanian;lumbaart;Luxembourgish;Malagasy;Malay;Nahuatl;Norwegian (bokmal);Norwegian Nynorsk;Novial;Occitan;Piedmontese;Portuguese;Romanian;Scots;Scottish Gaelic;Serbo-Croatian;Shona;Simple English;Slovenian;Spanish;Swahili;Swedish;Tagalog;Tatar;Turkish;Upper Sorbian;Vietnamese;veneto;Waray;Welsh;Western Frisian;Yoruba">Doha</name>
		<name normalized="Doho" languages="Esperanto">Doho</name>
		<name normalized="Doʻha" languages="Uzbek">Doʻha</name>
		<name normalized="Doha" languages="Asturian">Doḥa</name>
		<name normalized="Duoha" languages="Samogitian">Duoha</name>
		<name normalized="Dauha" languages="Volapuk">Däuha</name>
		<name normalized="Ντοχα" languages="Greek">Ντόχα</name>
		<name normalized="Goрad Doka" languages="Belarusian">Горад Доха</name>
		<name normalized="Dokae" languages="Ossetic">Дохæ</name>
		<name normalized="Doka" languages="Bulgarian;Chechen;Macedonian;Mongolian;Russian;Serbian;Ukrainian;biлaрuсkai (taрaskivita)‎">Доха</name>
		<name normalized="Doko" languages="Eastern Mari">Дохо</name>
		<name normalized="Doha" languages="Tajik">Доҳа</name>
		<name normalized="Dvhա" languages="Armenian">Դոհա</name>
		<name normalized="דvhh" languages="Hebrew">דוחה</name>
		<name normalized="אلدوhة" languages="Arabic">الدوحة</name>
		<name normalized="دوhh" languages="Mazanderani;Persian">دوحه</name>
		<name normalized="دوhہ" languages="Urdu;Western Punjabi">دوحہ</name>
		<name normalized="دوhא" languages="Pashto">دوها</name>
		<name normalized="دوھא" languages="Uyghur">دوھا</name>
		<name normalized="دەوhە" languages="Sorani Kurdish">دەوحە</name>
		<name normalized="dohा" languages="Marathi">दोहा</name>
		<name normalized="dohা" languages="Bengali">দোহা</name>
		<name normalized="dੋhਾ" languages="Punjabi">ਦੋਹਾ</name>
		<name normalized="தோகா" languages="Tamil">தோகா</name>
		<name normalized="ದೊಹಾ" languages="Kannada">ದೊಹಾ</name>
		<name normalized="ദോഹ" languages="Malayalam">ദോഹ</name>
		<name normalized="โดฮา" languages="Thai">โดฮา</name>
		<name normalized="དྷོ་ཧ།" languages="Tibetan">དྷོ་ཧ།</name>
		<name normalized="დოჰა" languages="Georgian;Mingrelian">დოჰა</name>
		<name normalized="ዶሃ" languages="Amharic">ዶሃ</name>
		<name normalized="dーh" languages="Japanese">ドーハ</name>
		<name normalized="多哈" languages="Cantonese;Chinese">多哈</name>
		<name normalized="도하" languages="Korean">도하</name>
	</region>
	<region name="Al Khawr wa adh Dhakhirah" type="municipality" typeTranslated="baladiyah">
		<name normalized="Al Khawr wa adh Dhakhirah" languages="English;official">Al Khawr wa adh Dhakhirah</name>
	</region>
	<region name="Al Wakrah" type="municipality" typeTranslated="baladiyah">
		<name normalized="Al Wakrah" languages="Catalan;Dutch;English;French;Irish;Italian;lumbaart;Malay;official;Spanish;Swedish;Tagalog;Vietnamese">Al Wakrah</name>
		<name normalized="Al-Wakra" languages="Finnish;German;Polish">Al-Wakra</name>
		<name normalized="Al-Wakrah" languages="Indonesian;Portuguese">Al-Wakrah</name>
		<name normalized="El Vakra" languages="Turkish">El Vakra</name>
		<name normalized="Vakra" languages="Lithuanian">Vakra</name>
		<name normalized="Aль-Vakрa" languages="Russian">Аль-Вакра</name>
		<name normalized="Vakрa" languages="Macedonian">Вакра</name>
		<name normalized="Uakрa" languages="Bulgarian">Уакра</name>
		<name normalized="אلوkrة" languages="Arabic">الوكرة</name>
		<name normalized="אلوکrh" languages="Mazanderani;Persian">الوکره</name>
		<name normalized="沃克拉" languages="Chinese">沃克拉</name>
		<name normalized="알와크라" languages="Korean">알와크라</name>
	</region>
	<region name="Ar Rayyan" type="municipality" typeTranslated="baladiyah">
		<name normalized="Al Rayyan" languages="English;French;Irish;Portuguese;Swedish;Vietnamese">Al Rayyan</name>
		<name normalized="Al-Rayyan" languages="Danish;Kalaallisut">Al-Rayyan</name>
		<name normalized="Ar Rayyan" languages="Catalan;Dutch;English;Italian;Malay;official">Ar Rayyan</name>
		<name normalized="Ar-Rajjan" languages="Polish">Ar-Rajjan</name>
		<name normalized="Ar-Rayyan" languages="Indonesian">Ar-Rayyan</name>
		<name normalized="Rajanas" languages="Lithuanian">Rajanas</name>
		<name normalized="Rayan" languages="Spanish">Rayán</name>
		<name normalized="Aр-Рaйiн" languages="Russian">Ар-Райян</name>
		<name normalized="Рajaн" languages="Macedonian">Рајан</name>
		<name normalized="אلryאن" languages="Arabic">الريان</name>
		<name normalized="rیאن" languages="Persian">ریان</name>
		<name normalized="riyーn" languages="Japanese">ライヤーン</name>
		<name normalized="알라얀" languages="Korean">알라얀</name>
	</region>
	<region name="Ash Shamal" type="municipality" typeTranslated="baladiyah">
		<name normalized="Al-Samal" languages="Finnish">Al-Šamal</name>
		<name normalized="Asch-Schamal" languages="German">Asch-Schamal</name>
		<name normalized="Ash Shamal" languages="Dutch;English;French;lumbaart;Norwegian (bokmal);official">Ash Shamal</name>
		<name normalized="Asz-Szamal" languages="Polish">Asz-Szamal</name>
		<name normalized="Madinat ash Shamal" languages="English;Italian;Portuguese;Swedish">Madinat ash Shamal</name>
		<name normalized="Madinat ash-Shamal" languages="Indonesian">Madinat ash-Shamal</name>
		<name normalized="Samalas" languages="Lithuanian">Šamalas</name>
		<name normalized="As-Saмaль" languages="Russian">Аш-Шамаль</name>
		<name normalized="Saмaл" languages="Macedonian">Шамал</name>
		<name normalized="אلشmאل" languages="Persian">الشمال</name>
		<name normalized="bلدyة אلشmאل" languages="Arabic">بلدية الشمال</name>
		<name normalized="아시샤말" languages="Korean">아시샤말</name>
	</region>
	<region name="Az Za'ayin" type="municipality" typeTranslated="baladiyah">
		<name normalized="Az Za'ayin" languages="English;official">Az Za'ayin</name>
		<name normalized="Az Zaayin" languages="English;official">Az Zaayin</name>
	</region>
	<region name="Umm Salal" type="municipality" typeTranslated="baladiyah">
		<name normalized="Um Salalas" languages="Lithuanian">Um Salalas</name>
		<name normalized="Umm Salal" languages="Dutch;English;French;Italian;lumbaart;official;Polish;Portuguese;Spanish">Umm Salal</name>
		<name normalized="Uм Сaлaл" languages="Macedonian">Ум Салал</name>
		<name normalized="Uмм-Сaлaль" languages="Russian">Умм-Салаль</name>
		<name normalized="אm sلאل" languages="Mazanderani;Persian">ام صلال</name>
		<name normalized="bلدyة أm sلאل" languages="Arabic">بلدية أم صلال</name>
		<name normalized="unm・srーr" languages="Japanese">ウンム・サラール</name>
		<name normalized="움살랄" languages="Korean">움살랄</name>
	</region>
</regions>
